[
  { "u": 0.818841, "v": 0.401449, "color": [51, 140, 255], "size": 5, "hz": 0, "phase": 0, "kind": "steady" },
  { "u": 0.821739, "v": 0.421739, "color": [51, 140, 255], "size": 5, "hz": 0, "phase": 0, "kind": "steady" },
  { "u": 0.827536, "v": 0.437681, "color": [51, 140, 255], "size": 5, "hz": 0, "phase": 0, "kind": "steady" },
  { "u": 0.836232, "v": 0.453623, "color": [51, 140, 255], "size": 5, "hz": 0, "phase": 0, "kind": "steady" },
  { "u": 0.0478261, "v": 0.724638, "color": [255, 26, 26], "size": 5, "hz": 0, "phase": 0, "kind": "steady" },
  { "u": 0.00289855, "v": 0.807246, "color": [255, 26, 26], "size": 5, "hz": 0, "phase": 0, "kind": "steady" },
  { "u": 0.105797, "v": 0.86087, "color": [255, 26, 26], "size": 5, "hz": 0, "phase": 0, "kind": "steady" }
]
