[
  { "u": 0.408696, "v": 0.081159, "color": [51, 140, 255], "size": 5, "hz": 0, "phase": 0, "kind": "steady" },
  { "u": 0.424638, "v": 0.078261, "color": [51, 140, 255], "size": 5, "hz": 0, "phase": 0, "kind": "steady" },
  { "u": 0.442029, "v": 0.071014, "color": [51, 140, 255], "size": 5, "hz": 0, "phase": 0, "kind": "steady" },
  { "u": 0.468116, "v": 0.065217, "color": [51, 140, 255], "size": 5, "hz": 0, "phase": 0, "kind": "steady" },
  { "u": 0.482609, "v": 0.055072, "color": [51, 140, 255], "size": 5, "hz": 0, "phase": 0, "kind": "steady" },
  { "u": 0.876812, "v": 0.910145, "color": [255, 26, 26], "size": 5, "hz": 0, "phase": 0, "kind": "steady" },
  { "u": 0.837681, "v": 0.998551, "color": [255, 26, 26], "size": 5, "hz": 0, "phase": 0, "kind": "steady" },
  { "u": 0.743478, "v": 0.957971, "color": [255, 26, 26], "size": 5, "hz": 0, "phase": 0, "kind": "steady" }
]
