[
  { "u": 0.0753623, "v": 0.226087, "color": [51, 140, 255], "size": 5, "hz": 0, "phase": 0, "kind": "steady" },
  { "u": 0.00869565, "v": 0.46087, "color": [51, 140, 255], "size": 5, "hz": 0, "phase": 0, "kind": "steady" },
  { "u": 0.244928, "v": 0.437681, "color": [51, 140, 255], "size": 5, "hz": 0, "phase": 0, "kind": "steady" },
  { "u": 0.226087, "v": 0.47971, "color": [51, 140, 255], "size": 5, "hz": 0, "phase": 0, "kind": "steady" },
  { "u": 0.321739, "v": 0.362319, "color": [51, 140, 255], "size": 5, "hz": 0, "phase": 0, "kind": "steady" },
  { "u": 0.223188, "v": 0.607246, "color": [51, 140, 255], "size": 5, "hz": 0, "phase": 0, "kind": "steady" },
  { "u": 0.813043, "v": 0.566667, "color": [255, 26, 26], "size": 5, "hz": 0, "phase": 0, "kind": "steady" },
  { "u": 0.711594, "v": 0.775362, "color": [255, 26, 26], "size": 5, "hz": 0, "phase": 0, "kind": "steady" }
]
