[
  {"u": 0.0536232, "v": 0.54058, "color": [255, 26, 26], "size": 20, "hz": 0, "phase": 0, "kind": "steady"},
  {"u": 0.292754, "v": 0.736232, "color": [255, 26, 26], "size": 20, "hz": 0, "phase": 0, "kind": "steady"},
  {"u": 0.724638, "v": 0.743478, "color": [255, 26, 26], "size": 20, "hz": 0, "phase": 0, "kind": "steady"},
  {"u": 0.942029, "v": 0.54058, "color": [255, 26, 26], "size": 20, "hz": 0, "phase": 0, "kind": "steady"},
  {"u": 0.513043, "v": 0.249275, "color": [51, 255, 57], "size": 40, "hz": 1.5, "phase": 0.46, "kind": "strobe"}
]
