[
  {"u": 0.457971, "v": 0.828986, "color": [255, 26, 26], "size": 20, "hz": 0, "phase": 0, "kind": "steady"},
  {"u": 0.484058, "v": 0.755072, "color": [255, 26, 26], "size": 20, "hz": 0, "phase": 0, "kind": "steady"},
  {"u": 0.446377, "v": 0.476812, "color": [255, 26, 26], "size": 20, "hz": 0, "phase": 0, "kind": "steady"},
  {"u": 0.247826, "v": 0.378261, "color": [255, 26, 26], "size": 20, "hz": 0, "phase": 0, "kind": "steady"},
  {"u": 0.852174, "v": 0.669565, "color": [51, 140, 255], "size": 40, "hz": 0, "phase": 0, "kind": "steady"},
  {"u": 0.915942, "v": 0.585507, "color": [51, 140, 255], "size": 40, "hz": 0, "phase": 0, "kind": "steady"},
  {"u": 0.805797, "v": 0.315942, "color": [51, 140, 255], "size": 40, "hz": 0, "phase": 0, "kind": "steady"},
  {"u": 0.671014, "v": 0.169565, "color": [51, 140, 255], "size": 40, "hz": 0, "phase": 0, "kind": "steady"}
]
