[
  { "u": 0.705882, "v": 0.422709, "color": [255, 26, 26], "size": 5, "hz": 0, "phase": 0, "kind": "steady" },
  { "u": 0.69357, "v": 0.589603, "color": [255, 26, 26], "size": 5, "hz": 0, "phase": 0, "kind": "steady" },
  { "u": 0.580027, "v": 0.592339, "color": [255, 26, 26], "size": 5, "hz": 0, "phase": 0, "kind": "steady" },
  { "u": 0.900137, "v": 0.44186, "color": [51, 140, 255], "size": 5, "hz": 0, "phase": 0, "kind": "steady" },
  { "u": 0.883721, "v": 0.586867, "color": [51, 140, 255], "size": 5, "hz": 0, "phase": 0, "kind": "steady" }
]
